pmodels/__init__.py
pmodels/comp.py
pmodels/ebm.py
pmodels/ht.py
pmodels/lin.py
pmodels-0.4.dist-info/licenses/LICENCE
pmodels-0.4.dist-info/METADATA
pmodels-0.4.dist-info/WHEEL
pmodels-0.4.dist-info/top_level.txt
pmodels-0.4.dist-info/RECORD
